sentencex-1.0.9.dist-info/METADATA
sentencex-1.0.9.dist-info/WHEEL
sentencex/__init__.py
sentencex/sentencex.cpython-314-x86_64-linux-gnu.so
sentencex-1.0.9.dist-info/RECORD
